roslibmsg/__init__.py
roslibmsg/geometry_msgs.py
roslibmsg/nav_msgs.py
roslibmsg-0.4.2.dist-info/LICENSE
roslibmsg-0.4.2.dist-info/METADATA
roslibmsg-0.4.2.dist-info/WHEEL
roslibmsg-0.4.2.dist-info/top_level.txt
roslibmsg-0.4.2.dist-info/RECORD
