Metadata-Version: 2.1
Name: roslibmsg
Version: 0.4.2
Summary: Unofficial implementation of msg for roslibpy
Author-email: OxygenLost <oxygenlostx@gmail.com>
Project-URL: Homepage, https://github.com/oxygenlost/roslibmsg
Project-URL: Bug Tracker, https://github.com/oxygenlost/roslibmsg/issues
Classifier: Development Status :: 5 - Production/Stable
Classifier: Intended Audience :: Developers
Classifier: License :: OSI Approved :: Apache Software License
Classifier: Operating System :: OS Independent
Classifier: Programming Language :: Python :: 3
Classifier: Programming Language :: Python :: 3.6
Classifier: Programming Language :: Python :: 3.7
Classifier: Programming Language :: Python :: 3.8
Classifier: Programming Language :: Python :: 3.9
Requires-Python: >=3.6
License-File: LICENSE
Requires-Dist: roslibpy
